airflow_chat/__init__.py
airflow_chat/plugins/README.md
airflow_chat/plugins/__init__.py
airflow_chat/plugins/airflow_chat.py
airflow_chat/plugins/app/__init__.py
airflow_chat/plugins/app/databases/__init__.py
airflow_chat/plugins/app/databases/postgres.py
airflow_chat/plugins/app/models/__init__.py
airflow_chat/plugins/app/models/inference/__init__.py
airflow_chat/plugins/app/models/inference/antropic_model.py
airflow_chat/plugins/app/models/inference/bedrock_model.py
airflow_chat/plugins/app/models/inference/openai_model.py
airflow_chat/plugins/app/server/__init__.py
airflow_chat/plugins/app/server/chat.py
airflow_chat/plugins/app/server/llm.py
airflow_chat/plugins/app/server/main.py
airflow_chat/plugins/app/utils/__init__.py
airflow_chat/plugins/app/utils/config.py
airflow_chat/plugins/app/utils/logger.py
airflow_chat/plugins/app/utils/singleton.py
airflow_chat/plugins/templates/chat_interface.html
airflow_chat/plugins/templates/dbt_upload.html
airflow_chat-0.1.0a13.dist-info/LICENSE
airflow_chat-0.1.0a13.dist-info/METADATA
airflow_chat-0.1.0a13.dist-info/WHEEL
airflow_chat-0.1.0a13.dist-info/entry_points.txt
airflow_chat-0.1.0a13.dist-info/RECORD
